api_urls.py
cgccli.py
cli_exceptions.py
subcommands/__init__.py
subcommands/config.py
subcommands/files.py
subcommands/projects.py
subcommands/whoami.py
utils/__init__.py
utils/configuration.py
utils/const.py
utils/helpers.py
utils/logger.py
cgccli-1.7.dist-info/LICENCE
cgccli-1.7.dist-info/METADATA
cgccli-1.7.dist-info/WHEEL
cgccli-1.7.dist-info/entry_points.txt
cgccli-1.7.dist-info/top_level.txt
cgccli-1.7.dist-info/RECORD
